django_simple_nav/__init__.py
django_simple_nav/_templates.py
django_simple_nav/_typing.py
django_simple_nav/apps.py
django_simple_nav/conf.py
django_simple_nav/jinja2.py
django_simple_nav/nav.py
django_simple_nav/py.typed
django_simple_nav/templatetags/__init__.py
django_simple_nav/templatetags/django_simple_nav.py
django_simple_nav-0.13.0.dist-info/METADATA
django_simple_nav-0.13.0.dist-info/WHEEL
django_simple_nav-0.13.0.dist-info/licenses/AUTHORS.md
django_simple_nav-0.13.0.dist-info/licenses/LICENSE
django_simple_nav-0.13.0.dist-info/RECORD
