Metadata-Version: 2.4
Name: django-simple-nav
Version: 0.13.0
Summary: A simple, flexible, and extensible navigation menu for Django.
Project-URL: Documentation, https://django-simple-nav.westervelt.dev/
Project-URL: Issues, https://github.com/westerveltco/django-simple-nav/issues
Project-URL: Source, https://github.com/westerveltco/django-simple-nav
Author-email: Josh Thomas <josh@joshthomas.dev>
License: MIT License
License-File: AUTHORS.md
License-File: LICENSE
Classifier: Development Status :: 4 - Beta
Classifier: Framework :: Django
Classifier: Framework :: Django :: 4.2
Classifier: Framework :: Django :: 5.0
Classifier: Framework :: Django :: 5.1
Classifier: Framework :: Django :: 5.2
Classifier: License :: OSI Approved :: MIT License
Classifier: Operating System :: OS Independent
Classifier: Programming Language :: Python
Classifier: Programming Language :: Python :: 3
Classifier: Programming Language :: Python :: 3 :: Only
Classifier: Programming Language :: Python :: 3.9
Classifier: Programming Language :: Python :: 3.10
Classifier: Programming Language :: Python :: 3.11
Classifier: Programming Language :: Python :: 3.12
Classifier: Programming Language :: Python :: 3.13
Classifier: Programming Language :: Python :: Implementation :: CPython
Requires-Python: >=3.9
Requires-Dist: django>=4.2
Provides-Extra: docs
Requires-Dist: cogapp>=3.4.1; extra == 'docs'
Requires-Dist: furo>=2024.8.6; extra == 'docs'
Requires-Dist: myst-parser>=3.0.1; extra == 'docs'
Requires-Dist: sphinx-autobuild>=2021.3.14; extra == 'docs'
Requires-Dist: sphinx-autodoc2>=0.5.0; extra == 'docs'
Requires-Dist: sphinx-copybutton>=0.5.2; extra == 'docs'
Requires-Dist: sphinx-inline-tabs>=2023.4.21; extra == 'docs'
Requires-Dist: sphinx>=7.1.2; extra == 'docs'
Provides-Extra: jinja2
Requires-Dist: jinja2; extra == 'jinja2'
Provides-Extra: tests
Requires-Dist: faker>=30.3.0; extra == 'tests'
Requires-Dist: model-bakery>=1.20.0; extra == 'tests'
Requires-Dist: pytest-cov>=5.0.0; extra == 'tests'
Requires-Dist: pytest-django>=4.9.0; extra == 'tests'
Requires-Dist: pytest-randomly>=3.15.0; extra == 'tests'
Requires-Dist: pytest-xdist>=3.6.1; extra == 'tests'
Requires-Dist: pytest>=8.3.3; extra == 'tests'
Provides-Extra: types
Requires-Dist: django-stubs-ext>=5.1.0; extra == 'types'
Requires-Dist: django-stubs>=5.1.0; extra == 'types'
Requires-Dist: mypy>=1.11.2; extra == 'types'
